.coveragerc
.travis.yml
CHANGES.rst
MANIFEST.in
Makefile
README.rst
setup.cfg
setup.py
tox.ini
avrsim/__init__.py
avrsim.egg-info/PKG-INFO
avrsim.egg-info/SOURCES.txt
avrsim.egg-info/dependency_links.txt
avrsim.egg-info/not-zip-safe
avrsim.egg-info/top_level.txt
tests/test_sanity.py