Metadata-Version: 1.1
Name: avrsim
Version: 0.1.2
Summary: An MyHDL simulator for AVR chips
Home-page: https://github.com/rblack42/AVRsim
Author: Roie R. Black
Author-email: rblack@austincc.edu
License: BSD 3-Clause
Platform: UNKNOWN
Classifier: Development Status :: 2 - Pre-Alpha
Classifier: License :: OSI Approved :: BSD License
Classifier: Operating System :: OS Independent
Classifier: Programming Language :: Python
Classifier: Programming Language :: Python :: 2.7
Classifier: Programming Language :: Python :: 3.5
Classifier: Natural Language :: English
Classifier: Intended Audience :: Developers
Classifier: Intended Audience :: Education
Classifier: Intended Audience :: Science/Research
